django_rulengine-0.0.4.dist-info/DESCRIPTION.rst
django_rulengine-0.0.4.dist-info/METADATA
django_rulengine-0.0.4.dist-info/RECORD
django_rulengine-0.0.4.dist-info/WHEEL
django_rulengine-0.0.4.dist-info/metadata.json
django_rulengine-0.0.4.dist-info/top_level.txt
djrulengine/__init__.py
djrulengine/admin.py
djrulengine/models.py
djrulengine/tests.py
djrulengine/utils.py
djrulengine/views.py
djrulengine/migrations/0001_initial.py
djrulengine/migrations/__init__.py
