Metadata-Version: 2.0
Name: django-rulengine
Version: 0.0.4
Summary: A simple rule engine for django admin
Home-page: https://github.com/ralkan/django-rulengine
Author: Resul Alkan
Author-email: me@resulalkan.com
License: MIT
Download-URL: https://github.com/ralkan/django-rulengine/tarball/0.0.4
Keywords: django,rule engine,django admin,admin rule engine
Platform: UNKNOWN
Requires-Dist: Django (>=1.7.10)
Requires-Dist: django-nested-inline (>=0.3.7)
Requires-Dist: rulengine (==0.0.6)
Requires-Dist: six (>=1.11)
